setup.py
cs1/__init__.py
cs1/graphics.py
cs1_graphics.egg-info/PKG-INFO
cs1_graphics.egg-info/SOURCES.txt
cs1_graphics.egg-info/dependency_links.txt
cs1_graphics.egg-info/requires.txt
cs1_graphics.egg-info/top_level.txt
dist/__init__.py