Metadata-Version: 2.1
Name: cs1-graphics
Version: 1.4
Summary: python 3 drawing library that takes calls similar to the cs1-graphics library and outputs with the turtle library
Home-page: https://github.com/jackSeigerman/cs1-graphics
Author: Jack Seigerman
Author-email: jacks3ds@gmail.com
Classifier: Programming Language :: Python :: 3
Classifier: License :: OSI Approved :: MIT License
Classifier: Operating System :: OS Independent
